{
  "a good": 0.00390625,
  "sounds": 0.00390625,
  "call the full": 0.00390625,
  "on the motherboard": 0.00390625,
  "chip actually there": 0.00390625,
  "confusion": 0.00390625,
  "news": 0.00390625,
  "in article": 0.00390625,
  "a centris": 0.00390625,
  "hate quotations": 0.00390625,
  "motorola doesnt call": 0.00390625,
  "deal but this": 0.00390625,
  "nate oo": 0.00390625,
  "state u engineering": 0.00390625,
  "funny system it": 0.00390625,
  "system it": 0.00390625,
  "number ralph": 0.00390625,
  "calling the": 0.00390625,
  "that motorola doesnt": 0.00390625,
  "is a funny": 0.00390625,
  "engineering": 0.00390625,
  "message": 0.00390625,
  "ralph waldo emerson": 0.00390625,
  "people that motorola": 0.00390625,
  "know nate sammons": 0.00390625,
  "a funny system": 0.00390625,
  "i hate": 0.00390625,
  "price drop": 0.00390625,
  "u engineering": 0.00390625,
  "for the confusion": 0.00390625,
  "sounds like a": 0.00390625,
  "waldo emerson oo": 0.00390625,
  "nathaniel sammons": 0.00390625,
  "engineering college in": 0.00390625,
  "writes nathaniel": 0.00390625,
  "quotations this": 0.00390625,
  "a redesign": 0.00390625,
  "hate quotations this": 0.00390625,
  "message brought you": 0.00390625,
  "writes nathaniel sammons": 0.00390625,
  "re price": 0.00390625,
  "alas this": 0.00390625,
  "system": 0.00390625,
  "deal but": 0.00390625,
  "coprocessor well": 0.00390625,
  "number of": 0.00390625,
  "gmt nntppostinghost cascolancecolostateedu": 0.00390625,
  "coprocessor since the": 0.00390625,
  "nate sammons": 0.00390625,
  "drop": 0.00390625,
  "the pseudodisclaimer": 0.00390625,
  "ralph waldo": 0.00390625,
  "this message brought": 0.00390625,
  "confusion nate": 0.00390625,
  "hd": 0.00390625,
  "oo ": 0.0078125,
  "ralph": 0.00390625,
  "state u": 0.00390625,
  "hardware": 0.00390625,
  "gmt nntppostinghost": 0.00390625,
  "nate sammons and": 0.00390625,
  "motorola doesnt": 0.00390625,
  "the confusion nate": 0.00390625,
  "nntppostinghost cascolancecolostateedu": 0.00390625,
  "quotations this message": 0.00390625,
  "good deal": 0.00390625,
  "this message": 0.00390625,
  "college in article": 0.00390625,
  "on within sender": 0.00390625,
  "the integrated": 0.00390625,
  "supposed to say": 0.00390625,
  "a funny": 0.00390625,
  "waldo": 0.00390625,
  "cascolancecolostateedu colorado state": 0.00390625,
  "sammons and the": 0.00390625,
  "the confusion": 0.00390625,
  "doesnt call the": 0.00390625,
  "know nate": 0.00390625,
  "built": 0.00390625,
  "without a coprocessor": 0.0078125,
  "colorado state u": 0.00390625,
  "ethernet": 0.00390625,
  "drop on": 0.00390625,
  "fpu": 0.0078125,
  "oo i hate": 0.00390625,
  "hd no ethernet": 0.00390625,
  "the number": 0.00390625,
  "i hate quotations": 0.00390625,
  "centris on": 0.00390625,
  "emerson": 0.00390625,
  "drop on within": 0.00390625,
  "redesign of": 0.00390625,
  "emerson oo ": 0.00390625,
  "no ethernet": 0.00390625,
  "alas": 0.00390625,
  "account thuapr": 0.00390625,
  "coprocessor its": 0.00390625,
  "price": 0.00390625,
  "article writes nathaniel": 0.00390625,
  "account": 0.00390625,
  "isnt": 0.00390625,
  "nathaniel sammons writes": 0.00390625,
  "funny": 0.00390625,
  "like a good": 0.00390625,
  "fullwhich people": 0.00390625,
  "writes": 0.0078125,
  "the full": 0.00390625,
  "quotations": 0.00390625,
  "college": 0.00390625,
  "simm hd no": 0.00390625,
  "calling": 0.00390625,
  "number of people": 0.00390625,
  "of the fullwhich": 0.00390625,
  "chip actually": 0.00390625,
  "sammons writes alas": 0.00390625,
  "and the number": 0.00390625,
  "the motherboard simm": 0.00390625,
  "within sender news": 0.00390625,
  "deal": 0.00390625,
  "emerson oo": 0.00390625,
  "news account": 0.00390625,
  "motherboard": 0.00390625,
  "sammons": 0.0078125,
  "coprocessor well actually": 0.00390625,
  "nntppostinghost": 0.00390625,
  "ethernet and": 0.00390625,
  "motherboard simm": 0.00390625,
  "number": 0.0078125,
  "the fullwhich": 0.00390625,
  "within sender": 0.00390625,
  "centris on the": 0.00390625,
  "call": 0.00390625,
  "state": 0.00390625,
  "nathaniel": 0.00390625,
  "into the chip": 0.00390625,
  "motherboard simm hd": 0.00390625,
  "brought": 0.00390625,
  "by a number": 0.00390625,
  "motorola": 0.00390625,
  "coprocessor its called": 0.00390625,
  "integrated": 0.00390625,
  "u": 0.00390625,
  "chip": 0.00390625,
  "a number": 0.00390625,
  "full": 0.00390625,
  "u engineering college": 0.00390625,
  "it just isnt": 0.00390625,
  "pseudodisclaimer is": 0.00390625,
  "doesnt": 0.00390625,
  "integrated fpu": 0.00390625,
  "built into the": 0.00390625,
  "fpu is built": 0.00390625,
  "waldo emerson": 0.00390625,
  "brought you": 0.00390625,
  "thuapr gmt": 0.00390625,
  "system it sounds": 0.00390625,
  "full that": 0.00390625,
  "pseudodisclaimer": 0.00390625,
  "college in": 0.00390625,
  "number ralph waldo": 0.00390625,
  "full that without": 0.00390625,
  "article": 0.00390625,
  "fullwhich": 0.00390625,
  "sammons writes": 0.00390625,
  "nate": 0.0078125,
  "writes alas": 0.00390625,
  "good deal but": 0.00390625,
  "writes alas this": 0.00390625,
  "are calling": 0.00390625,
  "since the fpu": 0.00390625,
  "redesign": 0.00390625,
  "the motherboard": 0.00390625,
  "and no coprocessor": 0.00390625,
  "centris": 0.00390625,
  "coprocessor since": 0.00390625,
  "isnt there thats": 0.00390625,
  "fullwhich people are": 0.00390625,
  "oo": 0.0078125,
  "sammons and": 0.00390625,
  "alas this is": 0.00390625,
  "is a centris": 0.00390625,
  "integrated fpu hardware": 0.00390625,
  "sender": 0.00390625,
  "account thuapr gmt": 0.00390625,
  "pseudodisclaimer is supposed": 0.00390625,
  "thuapr": 0.00390625,
  "calling the although": 0.00390625,
  "what the pseudodisclaimer": 0.00390625,
  "you know nate": 0.00390625,
  "oo i": 0.00390625,
  "supposed": 0.00390625,
  "doesnt call": 0.00390625,
  "article writes": 0.00390625,
  "nate oo i": 0.00390625,
  "colorado": 0.00390625,
  "engineering college": 0.00390625,
  "coprocessor": 0.01171875,
  "just isnt": 0.00390625,
  "thuapr gmt nntppostinghost": 0.00390625,
  "call the": 0.00390625,
  "hardware it": 0.00390625,
  "gmt": 0.00390625,
  "people are calling": 0.00390625,
  "the integrated fpu": 0.00390625,
  "redesign of the": 0.00390625,
  "funny system": 0.00390625,
  "hd no": 0.00390625,
  "re price drop": 0.00390625,
  "sender news": 0.00390625,
  "message brought": 0.00390625,
  "confusion nate oo": 0.00390625,
  "fpu hardware it": 0.00390625,
  "a coprocessor": 0.0078125,
  "ethernet and no": 0.00390625,
  "built into": 0.00390625,
  "the number ralph": 0.00390625,
  "sounds like": 0.00390625,
  "hate": 0.00390625,
  "is supposed": 0.00390625,
  "hardware it just": 0.00390625,
  "simm": 0.00390625,
  "is built": 0.00390625,
  "colorado state": 0.00390625,
  "it sounds": 0.00390625,
  "fpu is": 0.00390625,
  "fpu hardware": 0.00390625,
  "good": 0.00390625,
  "the chip": 0.00390625,
  "simm hd": 0.00390625,
  "cascolancecolostateedu colorado": 0.00390625,
  "price drop on": 0.00390625,
  "that motorola": 0.00390625,
  "sender news account": 0.00390625,
  "cascolancecolostateedu": 0.00390625,
  "is a redesign": 0.00390625,
  "brought you by": 0.00390625,
  "without the integrated": 0.00390625,
  "the fpu": 0.00390625,
  "a good deal": 0.00390625,
  "in article writes": 0.00390625,
  "nntppostinghost cascolancecolostateedu colorado": 0.00390625,
  "news account thuapr": 0.00390625,
  "no coprocessor": 0.00390625,
  "supposed to": 0.00390625,
  "isnt there": 0.00390625
}