{
  "thetranscedentaltemptation by paul": 0.015625,
  "origins": 0.015625,
  "mormonapr gmt": 0.015625,
  "kurtz has a": 0.015625,
  "book of mormonapr": 0.015625,
  "good section on": 0.015625,
  "astrophysicsworld fermiwustledu": 0.015625,
  "on the origins": 0.015625,
  "mormonapr": 0.015625,
  "gmt washington": 0.015625,
  "gmt washington university": 0.015625,
  "think that thetranscedentaltemptation": 0.015625,
  "re studies": 0.015625,
  "on book": 0.015625,
  "gmt": 0.015625,
  "kurtz has": 0.015625,
  "astrophysicsworld": 0.015625,
  "the origins": 0.015625,
  "at scott": 0.015625,
  "o ": 0.03125,
  "mormonism you might": 0.015625,
  "book of": 0.015625,
  "a good": 0.015625,
  "washington": 0.015625,
  "astrophysicsworld fermiwustledu i": 0.015625,
  "university astrophysicsworld": 0.015625,
  "studies": 0.015625,
  "paul kurtz has": 0.015625,
  "fermiwustledu": 0.015625,
  "scott o": 0.015625,
  "has a good": 0.015625,
  "mormonism": 0.015625,
  "university astrophysicsworld fermiwustledu": 0.015625,
  "fermiwustledu i think": 0.015625,
  "look at scott": 0.015625,
  "good": 0.015625,
  "thetranscedentaltemptation by": 0.015625,
  "studies on": 0.015625,
  "book": 0.015625,
  "of mormonism": 0.015625,
  "o": 0.015625,
  "scott o ": 0.015625,
  "kurtz": 0.015625,
  "studies on book": 0.015625,
  "paul": 0.015625,
  "scott": 0.015625,
  "origins of mormonism": 0.015625,
  "good section": 0.015625,
  "mormonism you": 0.015625,
  "that thetranscedentaltemptation": 0.015625,
  "at scott o": 0.015625,
  "university": 0.015625,
  "of mormonapr gmt": 0.015625,
  "washington university astrophysicsworld": 0.015625,
  "fermiwustledu i": 0.015625,
  "by paul kurtz": 0.015625,
  "mormonapr gmt washington": 0.015625,
  "by paul": 0.015625,
  "washington university": 0.015625,
  "paul kurtz": 0.015625,
  "origins of": 0.015625,
  "thetranscedentaltemptation": 0.015625,
  "of mormonapr": 0.015625
}