{
  "and misleading alan": 0.01,
  "stein ": 0.02,
  "gmt": 0.01,
  "are confusing": 0.01,
  "listening he": 0.01,
  "is racism": 0.02,
  "zionism is": 0.02,
  "zionism": 0.03,
  "stein": 0.01,
  "nysernet inc": 0.01,
  "tautological with": 0.01,
  "mean hear": 0.01,
  "statement i think": 0.01,
  "false and misleading": 0.01,
  "zionism is racism": 0.02,
  "zionism assuming": 0.01,
  "werent listening": 0.01,
  "writes so steve": 0.01,
  "false": 0.01,
  "assuming": 0.01,
  "alan h stein": 0.01,
  "re zionism": 0.01,
  "nysernet inc sunapr": 0.01,
  "hear you": 0.01,
  "sunapr gmt": 0.01,
  "with false": 0.01,
  "hear you werent": 0.01,
  "zionism assuming that": 0.01,
  "tautological statement": 0.01,
  "false and": 0.01,
  "alan h": 0.01,
  "confusing tautological": 0.01,
  "gmt d c": 0.01,
  "d c sessions": 0.01,
  "misleading": 0.01,
  "is a tautological": 0.01,
  "c sessions": 0.01,
  "confusing tautological with": 0.01,
  "assuming that you": 0.01,
  "racism this is": 0.01,
  "told you zionism": 0.01,
  "a tautological": 0.01,
  "are confusing tautological": 0.01,
  "assuming that": 0.01,
  "d c": 0.01,
  "racism": 0.02,
  "sunapr gmt d": 0.01,
  "racism nysernet inc": 0.01,
  "alan": 0.01,
  "racism nysernet": 0.01,
  "tautological": 0.02,
  "steve": 0.01,
  "sessions": 0.01,
  "statement i": 0.01,
  "is zionism": 0.01,
  "writes so": 0.01,
  "d": 0.01,
  "is zionism assuming": 0.01,
  "is racism nysernet": 0.01,
  "you werent listening": 0.01,
  "h": 0.01,
  "what is zionism": 0.01,
  "inc sunapr": 0.01,
  "listening": 0.01,
  "confusing": 0.01,
  "and misleading": 0.01,
  "h stein ": 0.01,
  "so steve": 0.01,
  "hear": 0.01,
  "tautological with false": 0.01,
  "sessions writes": 0.01,
  "nysernet": 0.01,
  "misleading alan": 0.01,
  "listening he just": 0.01,
  "inc sunapr gmt": 0.01,
  "writes": 0.01,
  "c sessions writes": 0.01,
  "sessions writes so": 0.01,
  "misleading alan h": 0.01,
  "you mean hear": 0.01,
  "statement": 0.01,
  "sunapr": 0.01,
  "racism this": 0.01,
  "steve lets": 0.01,
  "you zionism": 0.01,
  "steve lets here": 0.01,
  "c": 0.01,
  "tautological statement i": 0.01,
  "h stein": 0.01,
  "you are confusing": 0.01,
  "gmt d": 0.01,
  "a tautological statement": 0.01
}