{
  "re program": 0.015625,
  "sharware utilities": 0.015625,
  "two questions sender": 0.015625,
  "rice": 0.015625,
  "utilities": 0.015625,
  "news": 0.015625,
  "rice university monapr": 0.015625,
  "sender news rice": 0.015625,
  "you cn": 0.015625,
  "questions": 0.015625,
  "plugin bryan": 0.015625,
  "news rice university": 0.015625,
  "sender": 0.015625,
  "plugin": 0.015625,
  "questions sender": 0.015625,
  "monapr gmt": 0.015625,
  "program": 0.015625,
  "university": 0.015625,
  "bryan dunne ": 0.015625,
  "change both": 0.015625,
  "gmt": 0.015625,
  "utilities you": 0.015625,
  "sender news": 0.015625,
  "with several sharware": 0.015625,
  "questions sender news": 0.015625,
  "cn change": 0.015625,
  "change both my": 0.015625,
  "cn change both": 0.015625,
  "university monapr gmt": 0.015625,
  "monapr": 0.015625,
  "university monapr": 0.015625,
  "sharware utilities you": 0.015625,
  "cn": 0.015625,
  "change": 0.015625,
  "two questions": 0.015625,
  "manager two": 0.015625,
  "dunne": 0.015625,
  "manager": 0.015625,
  "bryan": 0.015625,
  "several sharware": 0.015625,
  "is plugin": 0.015625,
  "several sharware utilities": 0.015625,
  "plugin bryan dunne": 0.015625,
  "monapr gmt actually": 0.015625,
  "sharware": 0.015625,
  "program manager two": 0.015625,
  "gmt actually": 0.015625,
  "re program manager": 0.015625,
  "program manager": 0.015625,
  "utilities you cn": 0.015625,
  "gmt actually with": 0.015625,
  "you cn change": 0.015625,
  "fav": 0.015625,
  "is plugin bryan": 0.015625,
  "rice university": 0.015625,
  "news rice": 0.015625,
  "both my fav": 0.015625,
  "dunne ": 0.03125,
  "my fav": 0.015625,
  "fav is plugin": 0.015625,
  "bryan dunne": 0.015625,
  "fav is": 0.015625,
  "manager two questions": 0.015625
}